{"ak5Rn4OG6gPQZ4nKgYSwsA==":"mbr-1920x964.jpg","qI5acY+f1Uo6X+ISjFhbvw==":"mbr-1620x1080.jpg","UlzIJULaQCl0gXbRlV5XcA==":"mbr-1791x1080.jpg","OM6hTwqMAQpTVhLcPG86xg==":"background1.jpg","UAc7kepzJPkrSn4uqTRvmw==":"background4.jpg","HQaPD3RqCuEr9El3W5R1pQ==":"logo1-122x44.png","3Yt9inIaMaP4S+KIkNrJJw==":"logo1-1-122x44.png","Z9n7Q+F+C989Qm97/Kb84A==":"logo1-114x41.png","3qawftXdd6oB5bJYCD1J5Q==":"pai-66x59.png","jAxZUU/EwgY8uylA2hb67w==":"logo-582x347.png","9+vxWvqaAFeTjmeyz/IkUQ==":"cv-2000x1350.jpg","qBFzfI5dCDFcPhWh+23dbQ==":"docusign-vl8u46pvr6s-unsplash-304x203.jpeg","54ub9yhUTz9lpvymNFEMrw==":"florian-klauer-mk7d-4ucfmg-unsplash-2000x2933.jpg","mIIbxW0r7dEZSbMPwcoYdg==":"background2-1.jpg","q0Gpwz0zGw1D/pg6MT/asQ==":"background8-1.jpg","IY1WAU8xZVnoXcTwmE4R9Q==":"logo1-288x103.png","TgfRL+S+gN7oeh2PE1IWbQ==":"van-tay-media-kab_-4m4i74-unsplash-2000x1460.jpg","8ISArKxG7AGSQhItF789Kw==":"images%20(5)-304x166.jpeg","oks4ksrA19VTaPatL+ZEkQ==":"images%20(5)-304x166.jpeg","a+toqEQwQWzkHrX2EJOiQw==":"images%20(6)-318x106.jpeg","3avd5hdR0NvfSW0J4tEE6w==":"images%20(7)-260x186.jpeg","wZDqGTrlwZ75wOminsuEwg==":"first_bg-2000x1500.jpg"}